README.txt
setup.cfg
setup.py
collective/__init__.py
collective.roundabout.egg-info/PKG-INFO
collective.roundabout.egg-info/SOURCES.txt
collective.roundabout.egg-info/dependency_links.txt
collective.roundabout.egg-info/entry_points.txt
collective.roundabout.egg-info/namespace_packages.txt
collective.roundabout.egg-info/not-zip-safe
collective.roundabout.egg-info/paster_plugins.txt
collective.roundabout.egg-info/requires.txt
collective.roundabout.egg-info/top_level.txt
collective/roundabout/README.txt
collective/roundabout/__init__.py
collective/roundabout/config.py
collective/roundabout/configure.zcml
collective/roundabout/exportimport.py
collective/roundabout/interfaces.py
collective/roundabout/profiles.zcml
collective/roundabout/tests.py
collective/roundabout/browser/__init__.py
collective/roundabout/browser/browser.py
collective/roundabout/browser/configure.zcml
collective/roundabout/browser/images/arrow_e.gif
collective/roundabout/browser/images/arrow_e_over.gif
collective/roundabout/browser/images/arrow_n.gif
collective/roundabout/browser/images/arrow_n_over.gif
collective/roundabout/browser/images/arrow_ne.gif
collective/roundabout/browser/images/arrow_ne_over.gif
collective/roundabout/browser/images/arrow_nw.gif
collective/roundabout/browser/images/arrow_nw_over.gif
collective/roundabout/browser/images/arrow_s.gif
collective/roundabout/browser/images/arrow_s_over.gif
collective/roundabout/browser/images/arrow_se.gif
collective/roundabout/browser/images/arrow_se_over.gif
collective/roundabout/browser/images/arrow_sw.gif
collective/roundabout/browser/images/arrow_sw_over.gif
collective/roundabout/browser/images/arrow_w.gif
collective/roundabout/browser/images/arrow_w_over.gif
collective/roundabout/browser/images/compass_e.gif
collective/roundabout/browser/images/compass_n.gif
collective/roundabout/browser/images/compass_ne.gif
collective/roundabout/browser/images/compass_nw.gif
collective/roundabout/browser/images/compass_s.gif
collective/roundabout/browser/images/compass_se.gif
collective/roundabout/browser/images/compass_sw.gif
collective/roundabout/browser/images/compass_w.gif
collective/roundabout/browser/images/hotspot.gif
collective/roundabout/browser/images/image_hotspot_icon.gif
collective/roundabout/browser/images/image_icon.gif
collective/roundabout/browser/images/map_hotspot_icon.gif
collective/roundabout/browser/images/map_icon.gif
