Metadata-Version: 1.0
Name: collective.roundabout
Version: 0.3.1
Summary: Add support for 360 degree panoramic photos to your Plone site.
Home-page: http://www.fourdigits.nl
Author: Four Digits
Author-email: rob@fourdigits.nl
License: GPL
Keywords: roundabout 360 degrees viewer
Platform: UNKNOWN
Classifier: Framework :: Plone
Classifier: Programming Language :: Python
Classifier: Topic :: Software Development :: Libraries :: Python Modules
